deepillusion/__init__.py
deepillusion/_utils.py
deepillusion/_version.py
deepillusion/jaxattacks/__init__.py
deepillusion/tfattacks/__init__.py
deepillusion/torchattacks/__init__.py
deepillusion/torchattacks/_bim.py
deepillusion/torchattacks/_fgsm.py
deepillusion/torchattacks/_pgd.py
deepillusion/torchattacks/_rfgsm.py
deepillusion/torchattacks/_soft_attacks.py
deepillusion/torchattacks/_spsa.py
deepillusion/torchattacks/_utils.py
deepillusion/torchattacks/amp/__init__.py
deepillusion/torchattacks/amp/_bim.py
deepillusion/torchattacks/amp/_cw.py
deepillusion/torchattacks/amp/_fgsm.py
deepillusion/torchattacks/amp/_pgd.py
deepillusion/torchattacks/amp/_rfgsm.py
deepillusion/torchattacks/amp/_soft_attacks.py
deepillusion/torchattacks/analysis/__init__.py
deepillusion/torchattacks/analysis/_evaluate.py
deepillusion/torchattacks/analysis/_perturbation_statistics.py
deepillusion/torchattacks/analysis/plot/__init__.py
deepillusion/torchattacks/analysis/plot/_loss_landscape.py
deepillusion/torchattacks/analysis/plot/_plot_settings.py
deepillusion/torchdefenses/__init__.py
deepillusion/torchdefenses/_adversarial_train.py
deepillusion/torchdefenses/_trades_train.py
deepillusion/torchdefenses/amp/__init__.py
deepillusion/torchdefenses/amp/_adversarial_train.py
deepillusion-0.3.3.dist-info/LICENSE
deepillusion-0.3.3.dist-info/METADATA
deepillusion-0.3.3.dist-info/WHEEL
deepillusion-0.3.3.dist-info/top_level.txt
deepillusion-0.3.3.dist-info/RECORD
