Metadata-Version: 2.1
Name: deepillusion
Version: 0.3.3
Summary: Adversarial Machine Learning ToolBox
Home-page: https://github.com/metehancekic/deep-illusion.git
Author: Metehan Cekic
Author-email: metehancekic@ucsb.edu
License: MIT
Download-URL: https://github.com/metehancekic/deep-illusion/archive/v_033.tar.gz
Keywords: Adversarial,Attack,Pytorch
Platform: UNKNOWN
Classifier: Development Status :: 3 - Alpha
Classifier: Intended Audience :: Developers
Classifier: Topic :: Software Development :: Build Tools
Classifier: License :: OSI Approved :: MIT License
Classifier: Programming Language :: Python :: 3
Classifier: Programming Language :: Python :: 3.4
Classifier: Programming Language :: Python :: 3.5
Classifier: Programming Language :: Python :: 3.6
Requires-Dist: tqdm
Requires-Dist: numpy
